{"brands":{"COUNTRY LIFE":{"name":"COUNTRY LIFE","md5name":"2917f38451f09f89ce3178522b02ac5b","image":"","sale":true,"instock":true,"custom_image":false,"collection":false,"exclude":false,"favourite":false},"NATURE S PLUS":{"name":"NATURE S PLUS","md5name":"49c3d42281a209e9a1d3125fed99d29d","image":"","sale":true,"instock":true,"custom_image":false,"collection":false,"exclude":false,"favourite":false},"PATHWAY":{"name":"PATHWAY","md5name":"ecb126681dddee39a7ab0d93924e7b25","image":"","sale":true,"instock":true,"custom_image":false,"collection":false,"exclude":false,"favourite":false},"NOW":{"name":"NOW","md5name":"97bc592b27a9ada2d9a4bb418ed0ebed","image":"","sale":true,"instock":false,"custom_image":false,"collection":false,"exclude":false,"favourite":false},"REVIVA":{"name":"REVIVA","md5name":"02dad717e8dbe4144b9dd40d00f0c94e","image":"","sale":true,"instock":true,"custom_image":false,"collection":false,"exclude":false,"favourite":false},"ALLERGY RESEARCH GROUP":{"name":"ALLERGY RESEARCH GROUP","md5name":"e4634813c463a7ee10465622f86eb61b","image":"","sale":true,"instock":true,"custom_image":false,"collection":false,"exclude":false,"favourite":false},"THORNE RESEARCH":{"name":"THORNE RESEARCH","md5name":"c9be29312c362a3e87156900e2127eeb","image":"","sale":false,"instock":true,"custom_image":false,"collection":false,"exclude":false,"favourite":false},"DOUGLAS LABS":{"name":"DOUGLAS LABS","md5name":"3ccf9377ba7c011cbc6bc10d524522e8","image":"","sale":false,"instock":true,"custom_image":false,"collection":false,"exclude":false,"favourite":false},"SOLGAR":{"name":"SOLGAR","md5name":"57fc4ad70efa7aa4abccf6280f3eb4fb","image":"","sale":true,"instock":true,"custom_image":false,"collection":false,"exclude":false,"favourite":false},"SOLARAY":{"name":"SOLARAY","md5name":"a9ed471fd9c3862cc5e274c8eca59610","image":"","sale":true,"instock":true,"custom_image":false,"collection":false,"exclude":false,"favourite":false},"SOURCE NATURALS":{"name":"SOURCE NATURALS","md5name":"de6f8dfcb02990bfd290f093c89840bb","image":"","sale":true,"instock":true,"custom_image":false,"collection":false,"exclude":false,"favourite":false},"JARROW FORMULAS":{"name":"JARROW FORMULAS","md5name":"8bdf5d36a3c39b8c5e2f9b32b0d1ae6d","image":"","sale":true,"instock":true,"custom_image":false,"collection":false,"exclude":false,"favourite":false},"NOW FOODS":{"name":"NOW FOODS","md5name":"d14ffa7e249e01f07d387a716a306e63","image":"","sale":true,"instock":true,"custom_image":false,"collection":false,"exclude":false,"favourite":false},"XYMOGEN":{"name":"XYMOGEN","md5name":"c14ee99e40da9499a93785cfee7ca2d4","image":"","sale":true,"instock":true,"custom_image":false,"collection":false,"exclude":false,"favourite":false},"GARDEN OF LIFE":{"name":"GARDEN OF LIFE","md5name":"cb4012fbe5b5c730250db930880d0af0","image":"","sale":true,"instock":true,"custom_image":false,"collection":false,"exclude":false,"favourite":false},"TWIN LAB":{"name":"TWIN LAB","md5name":"d14ed905d6125fadc86011b6a98573f2","image":"","sale":true,"instock":true,"custom_image":false,"collection":false,"exclude":false,"favourite":false},"METAGENICS":{"name":"METAGENICS","md5name":"c826c274d0f35be093471532d97bd978","image":"","sale":false,"instock":true,"custom_image":false,"collection":false,"exclude":false,"favourite":false},"ENZYMATIC THERAPY":{"name":"ENZYMATIC THERAPY","md5name":"b60510406337596b66f1f383af53286f","image":"","sale":true,"instock":true,"custom_image":false,"collection":false,"exclude":false,"favourite":false},"REPUBLIC OF TEA":{"name":"REPUBLIC OF TEA","md5name":"af00b90c5fc692df6d1e23877cb76a6f","image":"","sale":true,"instock":true,"custom_image":false,"collection":false,"exclude":false,"favourite":false},"PURE ENCAPSULATIONS":{"name":"PURE ENCAPSULATIONS","md5name":"fab1d5ccef8ed1a014024eb24285c205","image":"","sale":true,"instock":true,"custom_image":false,"collection":false,"exclude":false,"favourite":false},"TWINLAB":{"name":"TWINLAB","md5name":"7b0cf626aee6b493a71080a8ef2c25ac","image":"","sale":true,"instock":true,"custom_image":false,"collection":false,"exclude":false,"favourite":false},"myvillagegreen":{"name":"myvillagegreen","md5name":"b7651a2bdaa98376d776e9461a8eb3bb","image":"","sale":true,"instock":true,"custom_image":false,"collection":false,"exclude":false,"favourite":false},"LIFE EXTENSION":{"name":"LIFE EXTENSION","md5name":"ce5134d58f5511e5630f5c607c5464c2","image":"","sale":true,"instock":true,"custom_image":false,"collection":false,"exclude":false,"favourite":false},"BOIRON":{"name":"BOIRON","md5name":"bc0dc9c761b934e6aeb591b187a66fc8","image":"","sale":true,"instock":true,"custom_image":false,"collection":false,"exclude":false,"favourite":false},"BHI MEDINATURA":{"name":"BHI MEDINATURA","md5name":"189b1977dfceeea8eff8425f7395e106","image":"","sale":false,"instock":true,"custom_image":false,"collection":false,"exclude":false,"favourite":false},"NELSONS HOMEOPATHICS":{"name":"NELSONS HOMEOPATHICS","md5name":"7c23089d55aca61e407f3b93b701f62a","image":"","sale":true,"instock":true,"custom_image":false,"collection":false,"exclude":false,"favourite":false},"NUTRANEXT":{"name":"NUTRANEXT","md5name":"22b88ca633fc2efbef6d955fd2da4e05","image":"","sale":true,"instock":false,"custom_image":false,"collection":false,"exclude":false,"favourite":false},"RAINBOW LIGHT":{"name":"RAINBOW LIGHT","md5name":"804e18ef714f75e5f7b4b997bdfa1f6f","image":"","sale":true,"instock":true,"custom_image":false,"collection":false,"exclude":false,"favourite":false},"INNATE RESPONSE":{"name":"INNATE RESPONSE","md5name":"ed70cf04ba2fd5266e2684c920cfc262","image":"","sale":false,"instock":true,"custom_image":false,"collection":false,"exclude":false,"favourite":false},"BIOTICS RESEARCH":{"name":"BIOTICS RESEARCH","md5name":"3faeb912411878f3363e05cfd3a1ad71","image":"","sale":true,"instock":true,"custom_image":false,"collection":false,"exclude":false,"favourite":false},"CARLSON":{"name":"CARLSON","md5name":"3efc15d786b9219dc285eff21e42f2a9","image":"","sale":true,"instock":true,"custom_image":false,"collection":false,"exclude":false,"favourite":false},"NEURO SCIENCE":{"name":"NEURO SCIENCE","md5name":"8bc11637b039e8bdca1066fb2738a47f","image":"","sale":false,"instock":false,"custom_image":false,"collection":false,"exclude":false,"favourite":false},"GAIA HERBS":{"name":"GAIA HERBS","md5name":"6ee939863c485af86b79c5ac611b522b","image":"","sale":true,"instock":true,"custom_image":false,"collection":false,"exclude":false,"favourite":false},"EMERSON ECOLOGICS":{"name":"EMERSON ECOLOGICS","md5name":"f2b41e64cadcd4ce3c1ba516695e7804","image":"","sale":true,"instock":true,"custom_image":false,"collection":false,"exclude":false,"favourite":false},"APEX ENERGETICS":{"name":"APEX ENERGETICS","md5name":"2b2694ab241941cad535fe20457af3eb","image":"","sale":false,"instock":false,"custom_image":false,"collection":false,"exclude":false,"favourite":false},"BLUE BONNET":{"name":"BLUE BONNET","md5name":"2d1161edb9baac13b423d4e564fec138","image":"","sale":true,"instock":true,"custom_image":false,"collection":false,"exclude":false,"favourite":false},"RAINBOW LIGHT NUTRIT":{"name":"RAINBOW LIGHT NUTRIT","md5name":"46eb54e3569228db1ab4181a14e32487","image":"","sale":false,"instock":true,"custom_image":false,"collection":false,"exclude":false,"favourite":false},"HUGO NATURALS":{"name":"HUGO NATURALS","md5name":"7213e628bed49ba59a1937c12948ede5","image":"","sale":true,"instock":false,"custom_image":false,"collection":false,"exclude":false,"favourite":false},"MAGSOOTHIUM":{"name":"MAGSOOTHIUM","md5name":"b6f2b6c52102f0bc8c21b02f34af9b74","image":"","sale":true,"instock":true,"custom_image":false,"collection":false,"exclude":false,"favourite":false},"HOST DEFENSE":{"name":"HOST DEFENSE","md5name":"f7ec297e42a20279f1a24be53e9e4ae6","image":"","sale":true,"instock":false,"custom_image":false,"collection":false,"exclude":false,"favourite":false},"DERMA E":{"name":"DERMA E","md5name":"25b278e2c2873c386b753e574e6216bc","image":"","sale":true,"instock":true,"custom_image":false,"collection":false,"exclude":false,"favourite":false},"LOGONA":{"name":"LOGONA","md5name":"315f62bddcc66b8d7e2b58536ca7a4b9","image":"","sale":true,"instock":true,"custom_image":false,"collection":false,"exclude":false,"favourite":false},"BACH FLOWER REMEDIES":{"name":"BACH FLOWER REMEDIES","md5name":"abd124290d17f4d73fc7756d3fae6e11","image":"","sale":true,"instock":true,"custom_image":false,"collection":false,"exclude":false,"favourite":false},"SINUS SURVIVAL":{"name":"SINUS SURVIVAL","md5name":"a812106f87464293c4a5e47bd018f0bf","image":"","sale":true,"instock":true,"custom_image":false,"collection":false,"exclude":false,"favourite":false},"BHI HEEL":{"name":"BHI HEEL","md5name":"6e1f86db78fcfef7366d99de364fae94","image":"","sale":false,"instock":true,"custom_image":false,"collection":false,"exclude":false,"favourite":false},"NATURE S WAY":{"name":"NATURE S WAY","md5name":"a81109be1de70df16e67dc5123ed2335","image":"","sale":true,"instock":true,"custom_image":false,"collection":false,"exclude":false,"favourite":false},"ALL ONE":{"name":"ALL ONE","md5name":"9f1d2a30e379fd151f2e9a5a5c7a4b81","image":"","sale":true,"instock":true,"custom_image":false,"collection":false,"exclude":false,"favourite":false},"BADGER":{"name":"BADGER","md5name":"7e59cb5b2f52c763bc846471fe5942e4","image":"","sale":true,"instock":true,"custom_image":false,"collection":false,"exclude":false,"favourite":false},"DAVINCI":{"name":"DAVINCI","md5name":"aea862aa22a0f5b829d5795882889c08","image":"","sale":false,"instock":true,"custom_image":false,"collection":false,"exclude":false,"favourite":false},"MEGAFOOD":{"name":"MEGAFOOD","md5name":"b7fafdbc80438ac8a7573bb6b914ad66","image":"","sale":true,"instock":true,"custom_image":false,"collection":false,"exclude":false,"favourite":false},"BLUEBONNET":{"name":"BLUEBONNET","md5name":"a3e4efb62497f6defa5e63eb695d963c","image":"","sale":true,"instock":false,"custom_image":false,"collection":false,"exclude":false,"favourite":false},"HIMALAYA USA":{"name":"HIMALAYA USA","md5name":"3792e3f14ad809d44769d67e5243309d","image":"","sale":true,"instock":true,"custom_image":false,"collection":false,"exclude":false,"favourite":false},"OLBAS":{"name":"OLBAS","md5name":"e873745441a689dd5400cc30bb9994a9","image":"","sale":true,"instock":true,"custom_image":false,"collection":false,"exclude":false,"favourite":false},"ALTEYA ORGANICS":{"name":"ALTEYA ORGANICS","md5name":"7d9c84780f360d300e3a77e89a5318a6","image":"","sale":true,"instock":true,"custom_image":false,"collection":false,"exclude":false,"favourite":false},"PURE ENCAPSULATION":{"name":"PURE ENCAPSULATION","md5name":"15d67cf17f9c44027c00de2ae0ff3915","image":"","sale":true,"instock":true,"custom_image":false,"collection":false,"exclude":false,"favourite":false},"PLANETARY FORMULATIONS":{"name":"PLANETARY FORMULATIONS","md5name":"655aa4c958eeb934440cb6fe8dfbbb40","image":"","sale":true,"instock":true,"custom_image":false,"collection":false,"exclude":false,"favourite":false},"MYCHELLE":{"name":"MYCHELLE","md5name":"de1e4dd752a4f57baae31802056abe6f","image":"","sale":true,"instock":true,"custom_image":false,"collection":false,"exclude":false,"favourite":false},"RAINBOW ACRES":{"name":"RAINBOW ACRES","md5name":"dea22003c1088a0a1e41785388aadcd1","image":"","sale":true,"instock":false,"custom_image":false,"collection":false,"exclude":false,"favourite":false},"NORDIC NATURALS":{"name":"NORDIC NATURALS","md5name":"66e57dd31e91d6a408781a9df5473fc0","image":"","sale":true,"instock":true,"custom_image":false,"collection":false,"exclude":false,"favourite":false},"NELSON'S":{"name":"NELSON'S","md5name":"9d6eec9d426d4983b6851500da39db61","image":"","sale":true,"instock":true,"custom_image":false,"collection":false,"exclude":false,"favourite":false},"HERBPHARM":{"name":"HERBPHARM","md5name":"9acc566d80e756689fb1f286bc54143e","image":"","sale":true,"instock":true,"custom_image":false,"collection":false,"exclude":false,"favourite":false},"NATURE SWAY":{"name":"NATURE SWAY","md5name":"12624dd5d7c19462ca0cd8f0169155f5","image":"","sale":true,"instock":false,"custom_image":false,"collection":false,"exclude":false,"favourite":false},"HYALOGIC":{"name":"HYALOGIC","md5name":"02ab1bc25ac915d92a4ca12c1ff10502","image":"","sale":true,"instock":false,"custom_image":false,"collection":false,"exclude":false,"favourite":false},"HERBS ETC":{"name":"HERBS ETC","md5name":"4f76b3690e6fd1992000c2a6118febe7","image":"","sale":true,"instock":true,"custom_image":false,"collection":false,"exclude":false,"favourite":false},"NEUROSCIENCE":{"name":"NEUROSCIENCE","md5name":"89d0af5bce37ee110fd8614220b031b8","image":"","sale":false,"instock":true,"custom_image":false,"collection":false,"exclude":false,"favourite":false},"SUPERIOR SOURCE":{"name":"SUPERIOR SOURCE","md5name":"510644762501ab022442471a20b04738","image":"","sale":true,"instock":false,"custom_image":false,"collection":false,"exclude":false,"favourite":false},"AUBREY ORGANICS":{"name":"AUBREY ORGANICS","md5name":"f78737392402f4998eef7a7ec143d3bc","image":"","sale":true,"instock":true,"custom_image":false,"collection":false,"exclude":false,"favourite":false},"ALTEYA":{"name":"ALTEYA","md5name":"340a06905f3e40a31464e07395fe9557","image":"","sale":true,"instock":true,"custom_image":false,"collection":false,"exclude":false,"favourite":false},"GODDESS GARDEN":{"name":"GODDESS GARDEN","md5name":"3fb20e0d7db5982cab042a2c588a07bf","image":"","sale":true,"instock":false,"custom_image":false,"collection":false,"exclude":false,"favourite":false},"INCREDIWEAR":{"name":"INCREDIWEAR","md5name":"b463f86defc7fa52a34eac5338851837","image":"","sale":false,"instock":true,"custom_image":false,"collection":false,"exclude":false,"favourite":false},"TRUE BOTANICA":{"name":"TRUE BOTANICA","md5name":"9871469c3c8b4a88aebca1e9a58281fa","image":"","sale":true,"instock":false,"custom_image":false,"collection":false,"exclude":false,"favourite":false},"VALLEY GREEN":{"name":"VALLEY GREEN","md5name":"e9267ad5c247b5e4610139fe280fecfc","image":"","sale":true,"instock":false,"custom_image":false,"collection":false,"exclude":false,"favourite":false},"NEW CHAPTER":{"name":"NEW CHAPTER","md5name":"ac244caa8d0275fbdd5fd4d7008f99b2","image":"","sale":true,"instock":true,"custom_image":false,"collection":false,"exclude":false,"favourite":false},"ALLERGY RESEARCH GRO":{"name":"ALLERGY RESEARCH GRO","md5name":"967e00fcaaed79bccd1590e3e31341c0","image":"","sale":true,"instock":true,"custom_image":false,"collection":false,"exclude":false,"favourite":false},"WELEDA":{"name":"WELEDA","md5name":"3f91d3df38df68fffc43c9eefa3c64c7","image":"","sale":true,"instock":true,"custom_image":false,"collection":false,"exclude":false,"favourite":false},"KAMEDIS":{"name":"KAMEDIS","md5name":"a26da19f4bd4d90e618585efec151a3e","image":"","sale":false,"instock":false,"custom_image":false,"collection":false,"exclude":false,"favourite":false},"SANTE":{"name":"SANTE","md5name":"5ee85a3a67f83f7a0c52bda9dd3e74a5","image":"","sale":true,"instock":true,"custom_image":false,"collection":false,"exclude":false,"favourite":false},"BARLEAN S ORGANIC OILS":{"name":"BARLEAN S ORGANIC OILS","md5name":"12c81da77823d08825f4218eeeb04b4b","image":"","sale":true,"instock":true,"custom_image":false,"collection":false,"exclude":false,"favourite":false},"ONCOQOL":{"name":"ONCOQOL","md5name":"0f1dcec36398eb8dd0611af951b8bf02","image":"","sale":true,"instock":true,"custom_image":false,"collection":false,"exclude":false,"favourite":false},"TRADITIONAL MEDICINAL":{"name":"TRADITIONAL MEDICINAL","md5name":"7928545d9b9df45ee4854f7241949035","image":"","sale":true,"instock":false,"custom_image":false,"collection":false,"exclude":false,"favourite":false},"BARLEANS":{"name":"BARLEANS","md5name":"06cb648def8180b08f2d7dfb4266e6eb","image":"","sale":true,"instock":true,"custom_image":false,"collection":false,"exclude":false,"favourite":false},"SKINCANDO":{"name":"SKINCANDO","md5name":"b0d91a6fbbe1d1598fcc05e3b004ee66","image":"","sale":true,"instock":true,"custom_image":false,"collection":false,"exclude":false,"favourite":false},"SOPHYTOPRO":{"name":"SOPHYTOPRO","md5name":"3520aab15c3ac7ceff2aefe2e8fc27a9","image":"","sale":true,"instock":false,"custom_image":false,"collection":false,"exclude":false,"favourite":false},"DESIGNS FOR HEALTH":{"name":"DESIGNS FOR HEALTH","md5name":"73e39cbd553c4135b7320ec4d4625dc1","image":"","sale":true,"instock":false,"custom_image":false,"collection":false,"exclude":false,"favourite":false},"ALOE LIFE":{"name":"ALOE LIFE","md5name":"eb7ccfa21b2882e51deadc410336f698","image":"","sale":true,"instock":true,"custom_image":false,"collection":false,"exclude":false,"favourite":false},"BULLETPROOF":{"name":"BULLETPROOF","md5name":"a7ef6fcac8eeb25a8618c9857e21c120","image":"","sale":false,"instock":false,"custom_image":false,"collection":false,"exclude":false,"favourite":false},"PLANETARY FORMULAS":{"name":"PLANETARY FORMULAS","md5name":"3b42212bac4f40b91cd723b9b7dd7a16","image":"","sale":true,"instock":true,"custom_image":false,"collection":false,"exclude":false,"favourite":false},"BODYCEUTICALS ORGANIC BODYCARE":{"name":"BODYCEUTICALS ORGANIC BODYCARE","md5name":"1542fa5190b08cdc305a0ae3629689ec","image":"","sale":true,"instock":true,"custom_image":false,"collection":false,"exclude":false,"favourite":false},"FLORA INC":{"name":"FLORA INC","md5name":"781405954a2dd70cfc40b8c403ccced6","image":"","sale":true,"instock":true,"custom_image":false,"collection":false,"exclude":false,"favourite":false},"WELLEDA":{"name":"WELLEDA","md5name":"732a51ca03bc13867466d917f4dc5e35","image":"","sale":true,"instock":true,"custom_image":false,"collection":false,"exclude":false,"favourite":false},"MILLER PHARMACEUTICA":{"name":"MILLER PHARMACEUTICA","md5name":"e32c011a5620da872df82e5a9abb29e4","image":"","sale":true,"instock":true,"custom_image":false,"collection":false,"exclude":false,"favourite":false},"INTEGRATIVE THERAPUTIC":{"name":"INTEGRATIVE THERAPUTIC","md5name":"28bb321ca1f61dd6119782c8d21ff666","image":"","sale":true,"instock":true,"custom_image":false,"collection":false,"exclude":false,"favourite":false},"NEXT TO NATURE":{"name":"NEXT TO NATURE","md5name":"77637269fa4f500d16491793d6868fb6","image":"","sale":false,"instock":false,"custom_image":false,"collection":false,"exclude":false,"favourite":false},"KIRKMAN":{"name":"KIRKMAN","md5name":"03363119391e1d1babb397f75e070a06","image":"","sale":true,"instock":true,"custom_image":false,"collection":false,"exclude":false,"favourite":false},"BRIGIT TRUE ORGANICS":{"name":"BRIGIT TRUE ORGANICS","md5name":"d3138bcfa3d8f2a6b1e40930b5209ece","image":"","sale":true,"instock":true,"custom_image":false,"collection":false,"exclude":false,"favourite":false},"RENEW LIFE":{"name":"RENEW LIFE","md5name":"e8a45325c9650b438ddd74bab4751dd9","image":"","sale":true,"instock":true,"custom_image":false,"collection":false,"exclude":false,"favourite":false},"PETGUARD INC":{"name":"PETGUARD INC","md5name":"6b07dad1e5d8e273d5d99e6eeb4dacdd","image":"","sale":true,"instock":true,"custom_image":false,"collection":false,"exclude":false,"favourite":false},"CV Sciences":{"name":"CV Sciences","md5name":"a3c344c036435af1cb213d80f2d57d8a","image":"","sale":true,"instock":false,"custom_image":false,"collection":false,"exclude":false,"favourite":false},"CBD":{"name":"CBD","md5name":"e8c71ae8260892279214998d56e55b8e","image":"","sale":true,"instock":false,"custom_image":false,"collection":false,"exclude":false,"favourite":false},"LUMINA HEALTH PRODUC":{"name":"LUMINA HEALTH PRODUC","md5name":"ec53a45b94953062bf0b5c6320bb4715","image":"","sale":true,"instock":false,"custom_image":false,"collection":false,"exclude":false,"favourite":false},"NATURE'S WAY":{"name":"NATURE'S WAY","md5name":"36197d9c81ee252ef5c19bdb24d01d88","image":"","sale":true,"instock":true,"custom_image":false,"collection":false,"exclude":false,"favourite":false},"COLLECTIVE WELL BEIN":{"name":"COLLECTIVE WELL BEIN","md5name":"51446757add4fc513d694fe379c312af","image":"","sale":true,"instock":true,"custom_image":false,"collection":false,"exclude":false,"favourite":false},"MAXI HEALTH":{"name":"MAXI HEALTH","md5name":"532eaf1ef7a5fbda2649118188247b6d","image":"","sale":true,"instock":true,"custom_image":false,"collection":false,"exclude":false,"favourite":false},"NATURES PLUS":{"name":"NATURES PLUS","md5name":"76ad77fad5523e22ae367e2b77748060","image":"","sale":true,"instock":false,"custom_image":false,"collection":false,"exclude":false,"favourite":false},"TOM S OF MIANE":{"name":"TOM S OF MIANE","md5name":"32512b5f42353f20883f382e90a8f2c2","image":"","sale":true,"instock":false,"custom_image":false,"collection":false,"exclude":false,"favourite":false},"TOM S OF MAINE":{"name":"TOM S OF MAINE","md5name":"df160ed2b9c5fbd508d3011b06c86220","image":"","sale":true,"instock":false,"custom_image":false,"collection":false,"exclude":false,"favourite":false},"SOURCE NATURAL":{"name":"SOURCE NATURAL","md5name":"f122b3a965e19c87230a3085617ccc52","image":"","sale":true,"instock":true,"custom_image":false,"collection":false,"exclude":false,"favourite":false},"RUNA":{"name":"RUNA","md5name":"c42971270a4e9b23d9f118c5fe8ad727","image":"","sale":true,"instock":true,"custom_image":false,"collection":false,"exclude":false,"favourite":false},"BIOCHEM":{"name":"BIOCHEM","md5name":"bc4b143819bc3cc2f265d24b6fd0bf76","image":"","sale":true,"instock":true,"custom_image":false,"collection":false,"exclude":false,"favourite":false},"DR HAUSCHKA SKIN CA":{"name":"DR HAUSCHKA SKIN CA","md5name":"877f20eef34f9ee580472af1eacfdb0d","image":"","sale":true,"instock":true,"custom_image":false,"collection":false,"exclude":false,"favourite":false},"DR. HAUSCHKA SKIN CA":{"name":"DR. HAUSCHKA SKIN CA","md5name":"b33e043e2a9f44027a71e9f05fae9a12","image":"","sale":true,"instock":true,"custom_image":false,"collection":false,"exclude":false,"favourite":false},"HALO":{"name":"HALO","md5name":"57f842286171094855e51fc3a541c1e2","image":"","sale":true,"instock":true,"custom_image":false,"collection":false,"exclude":false,"favourite":false},"ALACER":{"name":"ALACER","md5name":"2f2a6f59a703d466c99b470ee74c02e9","image":"","sale":true,"instock":true,"custom_image":false,"collection":false,"exclude":false,"favourite":false},"OMEGA NUTRITION":{"name":"OMEGA NUTRITION","md5name":"5c9727165282f35e1b51f69fb3fb0a5e","image":"","sale":true,"instock":false,"custom_image":false,"collection":false,"exclude":false,"favourite":false},"QUANTUM":{"name":"QUANTUM","md5name":"370757d2df51ae456bf63c165fc71817","image":"","sale":true,"instock":true,"custom_image":false,"collection":false,"exclude":false,"favourite":false},"HIMALAYA HERBAL":{"name":"HIMALAYA HERBAL","md5name":"142984daff641f52212119d838559733","image":"","sale":true,"instock":false,"custom_image":false,"collection":false,"exclude":false,"favourite":false},"PLANT FUSION":{"name":"PLANT FUSION","md5name":"b676505e137c93938f1e4d193f603585","image":"","sale":true,"instock":true,"custom_image":false,"collection":false,"exclude":false,"favourite":false},"DR HAUSCHKA":{"name":"DR HAUSCHKA","md5name":"a1de2f09f521c55e53b55675b5ece53c","image":"","sale":true,"instock":true,"custom_image":false,"collection":false,"exclude":false,"favourite":false},"CARDIOVASCULAR RESEARCH":{"name":"CARDIOVASCULAR RESEARCH","md5name":"70ef42fcf72ac7fb33b6c97f50642647","image":"","sale":true,"instock":true,"custom_image":false,"collection":false,"exclude":false,"favourite":false},"NUTRAMAX LABS":{"name":"NUTRAMAX LABS","md5name":"1ce488bb9a9fc2d85d95f8a42000ab3f","image":"","sale":false,"instock":true,"custom_image":false,"collection":false,"exclude":false,"favourite":false},"DR HAUSCHKA SKIN CARE":{"name":"DR HAUSCHKA SKIN CARE","md5name":"304f095ffd7e296ea8ee3c45cada36d4","image":"","sale":true,"instock":true,"custom_image":false,"collection":false,"exclude":false,"favourite":false},"THAYERS":{"name":"THAYERS","md5name":"a4121f5d745d96f4a6aab8c8b96aaa4b","image":"","sale":true,"instock":true,"custom_image":false,"collection":false,"exclude":false,"favourite":false},"SALCURA":{"name":"SALCURA","md5name":"c49e4bf6f7a0357d3333a209540f19cc","image":"","sale":true,"instock":false,"custom_image":false,"collection":false,"exclude":false,"favourite":false},"DESERT ESSENCE":{"name":"DESERT ESSENCE","md5name":"27f02b1b8e6ba26e9391925082794fe7","image":"","sale":true,"instock":false,"custom_image":false,"collection":false,"exclude":false,"favourite":false},"EGYPTIAN MAGIC CREAM":{"name":"EGYPTIAN MAGIC CREAM","md5name":"480737cf8fbd5d2ba88853ba8493ca65","image":"","sale":true,"instock":false,"custom_image":false,"collection":false,"exclude":false,"favourite":false},"EMERGEN C":{"name":"EMERGEN C","md5name":"049a9ff4a887321e9cf2fd02883cd9c8","image":"","sale":true,"instock":true,"custom_image":false,"collection":false,"exclude":false,"favourite":false},"ALBA BOTANICA":{"name":"ALBA BOTANICA","md5name":"23e5fb8e7dab1aee3b09b3b86cd0ab30","image":"","sale":false,"instock":false,"custom_image":false,"collection":false,"exclude":false,"favourite":false},"AMERICAN HEALTH":{"name":"AMERICAN HEALTH","md5name":"661824ba278a4099d68df9a55aff2968","image":"","sale":true,"instock":true,"custom_image":false,"collection":false,"exclude":false,"favourite":false},"KYOLIC":{"name":"KYOLIC","md5name":"4473e2f9aea02517207154daf02e2842","image":"","sale":true,"instock":true,"custom_image":false,"collection":false,"exclude":false,"favourite":false},"VALLEY GREEN NATURALS":{"name":"VALLEY GREEN NATURALS","md5name":"614de7e276f4c558ef6c2f2cb0654c76","image":"","sale":true,"instock":false,"custom_image":false,"collection":false,"exclude":false,"favourite":false},"BORLIND OF GERMANY":{"name":"BORLIND OF GERMANY","md5name":"4388785bfee672ff761e0f6e8fb43978","image":"","sale":true,"instock":true,"custom_image":false,"collection":false,"exclude":false,"favourite":false},"YOGI TEA":{"name":"YOGI TEA","md5name":"051eb69d85027c847ed61fd6021e306c","image":"","sale":true,"instock":true,"custom_image":false,"collection":false,"exclude":false,"favourite":false},"INTEGRATIVE THERAPEUTICS":{"name":"INTEGRATIVE THERAPEUTICS","md5name":"db84f1b9ddd77ce721230bccc368ad20","image":"","sale":true,"instock":false,"custom_image":false,"collection":false,"exclude":false,"favourite":false},"VIBRANT HEALTH":{"name":"VIBRANT HEALTH","md5name":"3d488aca193470154a30c79f0a1a2355","image":"","sale":true,"instock":true,"custom_image":false,"collection":false,"exclude":false,"favourite":false},"BARAKA":{"name":"BARAKA","md5name":"481ef83f3145fe37a5f40268bb87ca6b","image":"","sale":true,"instock":true,"custom_image":false,"collection":false,"exclude":false,"favourite":false},"FLORASTOR":{"name":"FLORASTOR","md5name":"e9e51554134af8c068603ef51df6aaf4","image":"","sale":true,"instock":true,"custom_image":false,"collection":false,"exclude":false,"favourite":false},"Y S ORGANIC BEE FARMS":{"name":"Y S ORGANIC BEE FARMS","md5name":"70789ca5c43440fc6d6a10502d9f7db1","image":"","sale":true,"instock":true,"custom_image":false,"collection":false,"exclude":false,"favourite":false},"JARROW FORMUILAS":{"name":"JARROW FORMUILAS","md5name":"ddaea95d94a3b6a9abdd583046538939","image":"","sale":true,"instock":false,"custom_image":false,"collection":false,"exclude":false,"favourite":false},"RUNA TEA":{"name":"RUNA TEA","md5name":"6776abe10d769a0e3d0502636da5e35a","image":"","sale":true,"instock":true,"custom_image":false,"collection":false,"exclude":false,"favourite":false},"TRADITIONAL MEDICINALS":{"name":"TRADITIONAL MEDICINALS","md5name":"3adcba6755fd0536adb6db84f9f543d6","image":"","sale":true,"instock":false,"custom_image":false,"collection":false,"exclude":false,"favourite":false},"DAVINCI LABORATORIES":{"name":"DAVINCI LABORATORIES","md5name":"79529fb9ca264b9b2dab3cc82befba42","image":"","sale":false,"instock":true,"custom_image":false,"collection":false,"exclude":false,"favourite":false},"HIGHLAND LABORATORIE":{"name":"HIGHLAND LABORATORIE","md5name":"4bd35350bb32ee4c3fdcb27c8d90799f","image":"","sale":true,"instock":false,"custom_image":false,"collection":false,"exclude":false,"favourite":false},"NATURE'S PLUS":{"name":"NATURE'S PLUS","md5name":"dd7a4ea5aa09d8d3c5908bd16195d91a","image":"","sale":true,"instock":true,"custom_image":false,"collection":false,"exclude":false,"favourite":false},"PROVENTIVE NUTRITION":{"name":"PROVENTIVE NUTRITION","md5name":"d9491d98015d89974a662b87777698de","image":"","sale":true,"instock":true,"custom_image":false,"collection":false,"exclude":false,"favourite":false},"PETGUARD":{"name":"PETGUARD","md5name":"70630aaa6d67985482ee3e424ab54666","image":"","sale":false,"instock":false,"custom_image":false,"collection":false,"exclude":false,"favourite":false},"ZAND HERBALS":{"name":"ZAND HERBALS","md5name":"3c1e1df47947f5c2de8962e791c18008","image":"","sale":true,"instock":true,"custom_image":false,"collection":false,"exclude":false,"favourite":false},"REPUBLIC TEA":{"name":"REPUBLIC TEA","md5name":"0ff269e7910e89e66d92bcfd8ae0a944","image":"","sale":true,"instock":true,"custom_image":false,"collection":false,"exclude":false,"favourite":false},"JARROW":{"name":"JARROW","md5name":"510faab5290f1bdcc31bac82ce0b68a3","image":"","sale":true,"instock":false,"custom_image":false,"collection":false,"exclude":false,"favourite":false},"SEDONA LABS":{"name":"SEDONA LABS","md5name":"f2c0df847f17bc57a2a13cf67ebfaccb","image":"","sale":true,"instock":false,"custom_image":false,"collection":false,"exclude":false,"favourite":false},"HIMALAYA":{"name":"HIMALAYA","md5name":"fd971fa62b387945f9c5dcd834c15a6c","image":"","sale":true,"instock":false,"custom_image":false,"collection":false,"exclude":false,"favourite":false},"BARAKA RED HOT CERAM":{"name":"BARAKA RED HOT CERAM","md5name":"8fefa4515cc9a703a11d632c4b9d5f13","image":"","sale":true,"instock":true,"custom_image":false,"collection":false,"exclude":false,"favourite":false},"KAPOW":{"name":"KAPOW","md5name":"367d86b548b0aae399c4240754eedad1","image":"","sale":true,"instock":false,"custom_image":false,"collection":false,"exclude":false,"favourite":false},"NOW FOOD":{"name":"NOW FOOD","md5name":"9cfb6f642064ffeb51079b07c60aa1a7","image":"","sale":true,"instock":false,"custom_image":false,"collection":false,"exclude":false,"favourite":false},"MARK II":{"name":"MARK II","md5name":"244dd5227a3a970a67d9dae8e350b4a0","image":"","sale":true,"instock":false,"custom_image":false,"collection":false,"exclude":false,"favourite":false},"CHI S ENTERPRISE":{"name":"CHI S ENTERPRISE","md5name":"63089b8ce16410e834ed415a62857556","image":"","sale":false,"instock":false,"custom_image":false,"collection":false,"exclude":false,"favourite":false},"THE SOURCE":{"name":"THE SOURCE","md5name":"67e9dc9ea295d4e8463686531fcb0b1c","image":"","sale":true,"instock":true,"custom_image":false,"collection":false,"exclude":false,"favourite":false},"PANDA":{"name":"PANDA","md5name":"ce61649168c4550c2f7acab92354dc6e","image":"","sale":true,"instock":true,"custom_image":false,"collection":false,"exclude":false,"favourite":false},"THERANEEM ORGANIX":{"name":"THERANEEM ORGANIX","md5name":"011d91d367972d13a114dfbd0cc466b1","image":"","sale":true,"instock":true,"custom_image":false,"collection":false,"exclude":false,"favourite":false},"THORNE RES":{"name":"THORNE RES","md5name":"b5ce8c748f046d5cfbc16765679fe87c","image":"","sale":false,"instock":true,"custom_image":false,"collection":false,"exclude":false,"favourite":false},"ASCENTA":{"name":"ASCENTA","md5name":"e5d715a5a884cff2383ad1714bcb463c","image":"","sale":true,"instock":true,"custom_image":false,"collection":false,"exclude":false,"favourite":false},"BARLEAN'S ORGANIC OILS":{"name":"BARLEAN'S ORGANIC OILS","md5name":"b33621c59b6408e1e2ff6184906e8098","image":"","sale":true,"instock":true,"custom_image":false,"collection":false,"exclude":false,"favourite":false},"LIFE EXTRENSION":{"name":"LIFE EXTRENSION","md5name":"e8681fc31bc37535f3337d1753061907","image":"","sale":true,"instock":false,"custom_image":false,"collection":false,"exclude":false,"favourite":false},"BODYCEUTICALS":{"name":"BODYCEUTICALS","md5name":"6529c133e4bdb3c8e3d3792b9733e9d8","image":"","sale":true,"instock":true,"custom_image":false,"collection":false,"exclude":false,"favourite":false},"REAL TIME PAIN RELIEF":{"name":"REAL TIME PAIN RELIEF","md5name":"b61890ac690916e5af95d81143f85407","image":"","sale":true,"instock":false,"custom_image":false,"collection":false,"exclude":false,"favourite":false},"NUTRAMEDIX":{"name":"NUTRAMEDIX","md5name":"bb53128130806f2da1c0720500c71ff4","image":"","sale":true,"instock":false,"custom_image":false,"collection":false,"exclude":false,"favourite":false},"THORNE":{"name":"THORNE","md5name":"d3cc4a8ed02103b61f7515b88e4d7f4d","image":"","sale":false,"instock":false,"custom_image":false,"collection":false,"exclude":false,"favourite":false},"MICRO ESSENTIAL LABO":{"name":"MICRO ESSENTIAL LABO","md5name":"905cb5c8ee80da8293ff5ce2e0a26753","image":"","sale":false,"instock":false,"custom_image":false,"collection":false,"exclude":false,"favourite":false},"BEZWECKEN":{"name":"BEZWECKEN","md5name":"bdd5e3832f9ee28c24929ffa7f0cb6bf","image":"","sale":false,"instock":true,"custom_image":false,"collection":false,"exclude":false,"favourite":false},"LIFEEXTENSION":{"name":"LIFEEXTENSION","md5name":"3b79a76999419536928ee8949e6bde17","image":"","sale":true,"instock":false,"custom_image":false,"collection":false,"exclude":false,"favourite":false},"NONIE OF BEVERLY HIL":{"name":"NONIE OF BEVERLY HIL","md5name":"afae8ce4e9e3b091186692605d786d84","image":"","sale":true,"instock":true,"custom_image":false,"collection":false,"exclude":false,"favourite":false},"NATROL":{"name":"NATROL","md5name":"e475922d43d5465126fbe1cae98b80b4","image":"","sale":true,"instock":false,"custom_image":false,"collection":false,"exclude":false,"favourite":false},"WELLGENIX":{"name":"WELLGENIX","md5name":"fa2620db32da10de874ff4f892f8ff4f","image":"","sale":true,"instock":false,"custom_image":false,"collection":false,"exclude":false,"favourite":false},"DESERT ESSENCE ORGAN":{"name":"DESERT ESSENCE ORGAN","md5name":"01a27cd0374a59c38fe6aa3a6d9a773a","image":"","sale":true,"instock":false,"custom_image":false,"collection":false,"exclude":false,"favourite":false},"MICHELLE":{"name":"MICHELLE","md5name":"2345f10bb948c5665ef91f6773b3e455","image":"","sale":true,"instock":false,"custom_image":false,"collection":false,"exclude":false,"favourite":false},"DR DUNNER":{"name":"DR DUNNER","md5name":"00a0ee2dc5f6798284f5e4fa33f2a2fb","image":"","sale":true,"instock":false,"custom_image":false,"collection":false,"exclude":false,"favourite":false},"NEL S BOOKS":{"name":"NEL S BOOKS","md5name":"4050a692510f8b26186defbc35d7f8b1","image":"","sale":true,"instock":true,"custom_image":false,"collection":false,"exclude":false,"favourite":false},"TOM'S OF MAINE":{"name":"TOM'S OF MAINE","md5name":"e3fc455bd0fd0ca1d6f08e044aa9802c","image":"","sale":false,"instock":true,"custom_image":false,"collection":false,"exclude":false,"favourite":false},"NATRA BIO":{"name":"NATRA BIO","md5name":"7b764dbd28c183510fda1d9830fd24bd","image":"","sale":true,"instock":false,"custom_image":false,"collection":false,"exclude":false,"favourite":false},"ALLERGYRESEARCH":{"name":"ALLERGYRESEARCH","md5name":"cf5c89100fc1b873c38f9f11974643b2","image":"","sale":true,"instock":false,"custom_image":false,"collection":false,"exclude":false,"favourite":false},"NELSON'S HOMEOPATHIC":{"name":"NELSON'S HOMEOPATHIC","md5name":"ac8161143db003bad2aabcf57cbfe72e","image":"","sale":true,"instock":true,"custom_image":false,"collection":false,"exclude":false,"favourite":false},"ALBA":{"name":"ALBA","md5name":"74efb8aac68e37c289dfcf260e19ab25","image":"","sale":true,"instock":true,"custom_image":false,"collection":false,"exclude":false,"favourite":false},"MEDINATURA":{"name":"MEDINATURA","md5name":"2e202e69fcf12a5cff7b1b13adbe9124","image":"","sale":false,"instock":false,"custom_image":false,"collection":false,"exclude":false,"favourite":false},"HERB PHARM":{"name":"HERB PHARM","md5name":"6ccb41e19d27cd890e7ae005390d0806","image":"","sale":true,"instock":false,"custom_image":false,"collection":false,"exclude":false,"favourite":false},"4 LIFE":{"name":"4 LIFE","md5name":"1ce662d1ec994ae7bc4584ca1d925c2a","image":"","sale":false,"instock":true,"custom_image":false,"collection":false,"exclude":false,"favourite":false},"A C GRACE":{"name":"A C GRACE","md5name":"a77b8ab5785af3ff09e975ef40c42675","image":"","sale":false,"instock":false,"custom_image":false,"collection":false,"exclude":false,"favourite":false},"NEW WAVE ENVIRO":{"name":"NEW WAVE ENVIRO","md5name":"3c02f8175a7555c192c313ac345245a7","image":"","sale":false,"instock":false,"custom_image":false,"collection":false,"exclude":false,"favourite":false},"PATHWAYS":{"name":"PATHWAYS","md5name":"0be49294c2316ae8f5b661f7b9d46c88","image":"","sale":true,"instock":false,"custom_image":false,"collection":false,"exclude":false,"favourite":false},"YOGI TEA 16 BAGS":{"name":"YOGI TEA 16 BAGS","md5name":"146d44c3fb49c89c99ea176a75469b53","image":"","sale":true,"instock":false,"custom_image":false,"collection":false,"exclude":false,"favourite":false}},"job_status":"completed","job_start_time":"2020-02-27 10:43:52 +0000","collections":{"4 life":{"item":"4 Life"},"a.c. grace":{"item":"A.C. Grace"},"acid reflux":{"item":"Acid Reflux"},"add or adhd":{"item":"ADD or ADHD"},"age & gender":{"item":"Age & Gender"},"alba botanica":{"item":"Alba Botanica"},"all one":{"item":"All One"},"allergies":{"item":"Allergies"},"allergies\/sinus":{"item":"Allergies\/Sinus"},"allergy":{"item":"Allergy"},"allergy & allergic rhinitis":{"item":"Allergy & Allergic Rhinitis"},"allergy research group":{"item":"Allergy Research Group"},"aloe life":{"item":"Aloe Life"},"alteya":{"item":"Alteya"},"american health":{"item":"American Health"},"ancient nutrition":{"item":"Ancient Nutrition"},"annemarie borlind":{"item":"Annemarie Borlind"},"anti-aging":{"item":"Anti-Aging"},"antibiotics & natural antibiotics":{"item":"Antibiotics & Natural Antibiotics"},"antioxidants":{"item":"Antioxidants"},"anxiety":{"item":"Anxiety"},"apex energenics":{"item":"Apex Energenics"},"arthritis":{"item":"Arthritis"},"aubrey organics":{"item":"Aubrey Organics"},"autism":{"item":"Autism"},"bach flowers (nelson)":{"item":"Bach Flowers (Nelson)"},"badger":{"item":"Badger"},"baraka":{"item":"Baraka"},"barlean's":{"item":"Barlean's"},"baudelaire":{"item":"Baudelaire"},"bhi medinatura":{"item":"BHI MediNatura"},"biochem":{"item":"BioChem"},"biotics research":{"item":"Biotics Research"},"blood pressure":{"item":"Blood Pressure"},"blood sugar":{"item":"Blood Sugar"},"bluebonnet":{"item":"Bluebonnet"},"bluebonnet kosher":{"item":"Bluebonnet Kosher"},"bodyceuticals":{"item":"Bodyceuticals"},"boiron":{"item":"Boiron"},"bones":{"item":"Bones"},"borlind of germany":{"item":"Borlind of Germany"},"brain":{"item":"Brain"},"brain health":{"item":"Brain Health"},"brands":{"item":"Brands"},"bulletproof":{"item":"Bulletproof"},"bundled products (extra savings)":{"item":"Bundled Products (Extra Savings)"},"calcium":{"item":"Calcium"},"candida":{"item":"Candida"},"candida & fungal sinusitis 171824906371":{"item":"Candida & Fungal Sinusitis 171824906371"},"candida (yeast)":{"item":"Candida (Yeast)"},"cardiovascular research":{"item":"Cardiovascular Research"},"carlson labs":{"item":"Carlson Labs"},"categories":{"item":"Categories"},"cbd and hemp":{"item":"CBD and Hemp"},"cellfood":{"item":"Cellfood"},"chi's enterprise":{"item":"Chi's Enterprise"},"children":{"item":"Children"},"children's health":{"item":"Children's Health"},"cholesterol":{"item":"Cholesterol"},"chronic sinusitis & sinus infection remedies":{"item":"Chronic Sinusitis & Sinus Infection Remedies"},"cold remedies":{"item":"Cold Remedies"},"cold-flu":{"item":"Cold-Flu"},"colds":{"item":"Colds"},"collective well being":{"item":"Collective Well Being"},"consultations":{"item":"Consultations"},"coq10":{"item":"CoQ10"},"core nutrition":{"item":"Core Nutrition"},"country life":{"item":"Country Life"},"cv hemp":{"item":"CV Hemp"},"cv sciences":{"item":"CV Sciences"},"davinci":{"item":"Davinci"},"depression":{"item":"Depression"},"derma e":{"item":"Derma E"},"desert essence":{"item":"Desert Essence"},"designs for health":{"item":"Designs for Health"},"detox":{"item":"Detox"},"detox & elimination":{"item":"Detox & Elimination"},"diet":{"item":"Diet"},"dietary support":{"item":"Dietary Support"},"digestion":{"item":"Digestion"},"digestive":{"item":"Digestive"},"digestive health":{"item":"Digestive Health"},"digital products and books":{"item":"Digital Products and Books"},"douglas labs":{"item":"Douglas Labs"},"dr. bronner's":{"item":"Dr. Bronner's"},"dr. dunner":{"item":"Dr. Dunner"},"dr. hauschka skin care":{"item":"Dr. Hauschka Skin Care"},"egyptian magic":{"item":"Egyptian Magic"},"emergenc":{"item":"EmergenC"},"emerson ecologics":{"item":"Emerson Ecologics"},"energy":{"item":"Energy"},"environmental health":{"item":"Environmental Health"},"enzymatic therapy":{"item":"Enzymatic Therapy"},"enzymedica":{"item":"Enzymedica"},"enzymes":{"item":"Enzymes"},"eo":{"item":"EO"},"essential components of a healthy diet":{"item":"Essential Components of a Healthy Diet"},"essential fatty acids":{"item":"Essential Fatty Acids"},"essential oils":{"item":"Essential Oils"},"essentials of healthy living":{"item":"Essentials of Healthy Living"},"evanhealy":{"item":"Evanhealy"},"exercise recommendations":{"item":"Exercise Recommendations"},"eye health":{"item":"Eye Health"},"featured products":{"item":"Featured Products"},"fish oil":{"item":"Fish Oil"},"flora, inc":{"item":"Flora, Inc"},"florastor":{"item":"Florastor"},"food allergies":{"item":"Food Allergies"},"frequently asked questions":{"item":"Frequently Asked Questions"},"gaia herbs":{"item":"Gaia Herbs"},"garden of life":{"item":"Garden of Life"},"gifts":{"item":"Gifts"},"goddess garden":{"item":"Goddess Garden"},"gum health":{"item":"Gum Health"},"hair, skin, & nails":{"item":"Hair, Skin, & Nails"},"halo purely for pets":{"item":"Halo Purely for Pets"},"headaches & migraines":{"item":"Headaches & Migraines"},"health":{"item":"Health"},"health concerns":{"item":"Health Concerns"},"health topics":{"item":"Health Topics"},"healthy air\/ respiratory health":{"item":"Healthy Air\/ Respiratory Health"},"healthy weight management":{"item":"Healthy Weight Management"},"heart & cardiovascular":{"item":"Heart & Cardiovascular"},"heart & cardiovascular health":{"item":"Heart & Cardiovascular Health"},"herb pharm":{"item":"Herb Pharm"},"herbs":{"item":"Herbs"},"herbs etc.":{"item":"Herbs Etc."},"himalaya usa":{"item":"Himalaya USA"},"homeopathic":{"item":"Homeopathic"},"hormone imbalance":{"item":"Hormone Imbalance"},"host defense":{"item":"Host Defense"},"how it works":{"item":"How It Works"},"hugo naturals":{"item":"Hugo Naturals"},"hyalogic":{"item":"Hyalogic"},"ignite":{"item":"Ignite"},"immune health":{"item":"Immune Health"},"incrediwear":{"item":"Incrediwear"},"inflammation":{"item":"Inflammation"},"inflammation\/pain reducing foods":{"item":"Inflammation\/Pain Reducing Foods"},"inika organic":{"item":"Inika Organic"},"innate response":{"item":"Innate Response"},"intro to ehl":{"item":"Intro to EHL"},"iqyou":{"item":"IQYOU"},"irritable bowel syndrome (ibs)":{"item":"Irritable Bowel Syndrome (IBS)"},"jarrow formulas":{"item":"Jarrow Formulas"},"jason":{"item":"Jason"},"jj virgin":{"item":"JJ Virgin"},"joint pain":{"item":"Joint Pain"},"joints & muscles":{"item":"Joints & Muscles"},"joints\/muscles":{"item":"Joints\/Muscles"},"kalastyle":{"item":"Kalastyle"},"kapow!":{"item":"KaPow!"},"kirkman":{"item":"Kirkman"},"kosher":{"item":"Kosher"},"kyolic":{"item":"Kyolic"},"lab":{"item":"Lab"},"lab tests":{"item":"Lab Tests"},"lewis labs":{"item":"Lewis Labs"},"life extension":{"item":"Life Extension"},"lifestyle support":{"item":"Lifestyle Support"},"magnesium":{"item":"Magnesium"},"magsoothium":{"item":"Magsoothium"},"maxi health kosher":{"item":"Maxi Health Kosher"},"medicinal oils and sprays":{"item":"Medicinal Oils and Sprays"},"megafood":{"item":"MegaFood"},"melissa b naturally":{"item":"Melissa B Naturally"},"memory":{"item":"Memory"},"men 20s & 30s":{"item":"Men 20s & 30s"},"men 40s & 50s":{"item":"Men 40s & 50s"},"men 60+":{"item":"Men 60+"},"menopause":{"item":"Menopause"},"menopause health":{"item":"Menopause Health"},"metabolic maintenance":{"item":"Metabolic Maintenance"},"metagenics":{"item":"Metagenics"},"miller pharma":{"item":"Miller Pharma"},"monthly membership":{"item":"Monthly Membership"},"mood":{"item":"Mood"},"mood & anxiety":{"item":"Mood & Anxiety"},"mt. angel":{"item":"Mt. Angel"},"multivitamin":{"item":"Multivitamin"},"mychelle":{"item":"MyChelle"},"nature science":{"item":"Nature Science"},"nature's plus":{"item":"Nature's Plus"},"nature's way":{"item":"Nature's Way"},"nelson's homeopathics":{"item":"Nelson's Homeopathics"},"neuroscience":{"item":"Neuroscience"},"new chapter":{"item":"New Chapter"},"new products":{"item":"New Products"},"next to nature":{"item":"Next to Nature"},"nordic naturals":{"item":"Nordic Naturals"},"now":{"item":"Now"},"now essential oils":{"item":"Now Essential Oils"},"nutralinks":{"item":"NutraLinks"},"nutramax labs inc.":{"item":"Nutramax Labs Inc."},"nutrigold":{"item":"NutriGold"},"nutrition":{"item":"Nutrition"},"nutrition now":{"item":"Nutrition Now"},"o'donnell":{"item":"O'Donnell"},"ocean blue":{"item":"Ocean Blue"},"oceana products":{"item":"Oceana Products"},"olbas\/penn herb":{"item":"Olbas\/Penn Herb"},"omega 3":{"item":"Omega 3"},"omega nutrition":{"item":"Omega Nutrition"},"oncoqol":{"item":"OncoQOL"},"osteoporosis":{"item":"Osteoporosis"},"pain management":{"item":"Pain Management"},"panda":{"item":"Panda"},"pathway":{"item":"Pathway"},"pathway sports nutrition":{"item":"Pathway Sports Nutrition"},"personal care":{"item":"Personal Care"},"pet guard":{"item":"Pet Guard"},"pet health":{"item":"Pet Health"},"pharmacy\/compounding":{"item":"Pharmacy\/Compounding"},"planetary formulations":{"item":"Planetary Formulations"},"plant fusion":{"item":"Plant Fusion"},"plant therapy":{"item":"Plant Therapy"},"pms":{"item":"PMS"},"premenstrual syndrome (pms)":{"item":"Premenstrual Syndrome (PMS)"},"prenatal":{"item":"Prenatal"},"probiotics":{"item":"Probiotics"},"product specials":{"item":"Product Specials"},"prostate health":{"item":"Prostate Health"},"protocols":{"item":"Protocols"},"pure encapsulations":{"item":"Pure Encapsulations"},"quantum":{"item":"Quantum"},"quicksilver scientific":{"item":"Quicksilver Scientific"},"rainbow light nutritional":{"item":"Rainbow Light Nutritional"},"real time pain relief":{"item":"Real Time Pain Relief"},"relaxation & stress management":{"item":"Relaxation & Stress Management"},"renew life":{"item":"Renew Life"},"republic of tea":{"item":"Republic of Tea"},"respiratory healer installments":{"item":"Respiratory Healer Installments"},"respiratory healer membership":{"item":"Respiratory Healer Membership"},"respiratory healer programs":{"item":"Respiratory Healer Programs"},"restore":{"item":"Restore"},"restricted brands":{"item":"Restricted Brands"},"restricted brands catalog":{"item":"Restricted Brands Catalog"},"reviva":{"item":"Reviva"},"runa":{"item":"Runa"},"salcura":{"item":"Salcura"},"sante":{"item":"Sante"},"sedona labs":{"item":"Sedona Labs"},"selecting, preparing & storing food":{"item":"Selecting, Preparing & Storing Food"},"shop":{"item":"Shop"},"sinus congestion & sinus pain":{"item":"Sinus Congestion & Sinus Pain"},"sinus survival":{"item":"Sinus Survival"},"sinus survival membership":{"item":"Sinus Survival Membership"},"sinus survival program":{"item":"Sinus Survival Program"},"skincando":{"item":"Skincando"},"sleep":{"item":"Sleep"},"sleep\/relaxation":{"item":"Sleep\/Relaxation"},"solaray":{"item":"Solaray"},"solgar":{"item":"Solgar"},"solgar kosher":{"item":"Solgar Kosher"},"sophytopro":{"item":"SophytoPro"},"source naturals":{"item":"Source Naturals"},"sparoom":{"item":"Sparoom"},"stress":{"item":"Stress"},"sunscreen":{"item":"Sunscreen"},"super sale":{"item":"Super Sale"},"superior source":{"item":"Superior Source"},"surgery & trauma":{"item":"Surgery & Trauma"},"teas":{"item":"Teas"},"teens":{"item":"Teens"},"terra wash":{"item":"Terra Wash"},"thayers":{"item":"Thayers"},"theraben":{"item":"Theraben"},"theraneem organix":{"item":"TheraNeem Organix"},"thorne research":{"item":"Thorne Research"},"thorneorganics\/dermaqol.":{"item":"ThorneOrganics\/DermaQOL."},"tom's of maine":{"item":"Tom's of Maine"},"trace minerals":{"item":"Trace Minerals"},"traditional medicinal teas":{"item":"Traditional Medicinal Teas"},"travel health":{"item":"Travel Health"},"trilogy":{"item":"Trilogy"},"tyler\/integrative therapeutics":{"item":"Tyler\/Integrative Therapeutics"},"valley green naturals":{"item":"Valley Green Naturals"},"vibrant health":{"item":"Vibrant Health"},"virginia first tea farm":{"item":"Virginia First Tea Farm"},"virtue skinfood":{"item":"Virtue Skinfood"},"vitamin a":{"item":"Vitamin A"},"vitamin b":{"item":"Vitamin B"},"vitamin c":{"item":"Vitamin C"},"vitamin d":{"item":"Vitamin D"},"vitamin e":{"item":"Vitamin E"},"water: hydration & health":{"item":"Water: Hydration & Health"},"weight management":{"item":"Weight Management"},"weleda":{"item":"Weleda"},"wellgenix":{"item":"Wellgenix"},"women 20s & 30s":{"item":"Women 20s & 30s"},"women 40s & 50s":{"item":"Women 40s & 50s"},"women 60+":{"item":"Women 60+"},"women pregnant & lactating":{"item":"Women Pregnant & Lactating"},"women's health":{"item":"Women's Health"},"xymogen":{"item":"Xymogen"},"y.s. organic bee farms":{"item":"Y.S. Organic Bee Farms"},"yogi tea":{"item":"Yogi Tea"},"zinc":{"item":"Zinc"}},"product_count":3560,"job_completed_time":"2020-02-27 10:44:01 +0000"}